VIKRAM_STT/__init__.py
vikram_stt-0.1.dist-info/METADATA
vikram_stt-0.1.dist-info/WHEEL
vikram_stt-0.1.dist-info/top_level.txt
vikram_stt-0.1.dist-info/RECORD
